fest/__init__.py
fest/facebook.py
fest/google.py
fest/heroku.py
fest/utils.py
fest-5.2.0.dist-info/LICENSE
fest-5.2.0.dist-info/WHEEL
fest-5.2.0.dist-info/METADATA
fest-5.2.0.dist-info/RECORD
