Metadata-Version: 2.1
Name: fest
Version: 5.2.0
Summary: Facebook Events Sync
Author-email: Alexander Mancevice <alexander.mancevice@hey.com>
Requires-Python: >= 3.7
Classifier: Development Status :: 3 - Alpha
Classifier: Intended Audience :: Developers
Classifier: Intended Audience :: System Administrators
Classifier: License :: OSI Approved :: MIT License
Classifier: License :: OSI Approved :: MIT License
Classifier: Operating System :: OS Independent
Classifier: Operating System :: OS Independent
Classifier: Programming Language :: Python :: 3
Classifier: Programming Language :: Python :: 3.7
Classifier: Programming Language :: Python :: 3.8
Classifier: Programming Language :: Python :: 3.9
Classifier: Programming Language :: Python :: 3.10
Classifier: Programming Language :: Python :: 3.11
Classifier: Programming Language :: Python :: 3.12
Classifier: Topic :: Utilities
Requires-Dist: facebook-sdk >= 3.0
Requires-Dist: google-api-python-client >= 1.6.4
Requires-Dist: requests >= 2.20
Project-URL: Home, https://github.com/amancevice/fest
